{
  "types": [
    "Road",
    "Track",
    "BMX",
    "MTB",
    "Cyclo Cross",
    "Speedway",
    "Time Trial",
    "Hill Climb"
  ],
  "regions": [
    "Central",
    "Eastern",
    "London & South East",
    "East Midlands",
    "West Midlands",
    "North East",
    "North West",
    "Scotland",
    "South",
    "South West",
    "Wales",
    "Yorkshire & Humber"
  ],
  "counts": {
    "Road": 9,
    "Track": 66,
    "BMX": 20,
    "MTB": 28,
    "Cyclo Cross": 97,
    "Speedway": 0,
    "Time Trial": 1,
    "Hill Climb": 110,
    "East Midlands": 33,
    "North East": 23,
    "Scotland": 27,
    "South": 30,
    "Central": 19,
    "South West": 29,
    "Wales": 36,
    "Yorkshire & Humber": 21,
    "London & South East": 35,
    "Eastern": 21,
    "West Midlands": 20,
    "North West": 37,
    "MTB|East Midlands": 12,
    "Hill Climb|North East": 12,
    "Track|East Midlands": 4,
    "Track|Scotland": 11,
    "Hill Climb|South": 10,
    "Cyclo Cross|Central": 11,
    "BMX|South West": 5,
    "MTB|Wales": 2,
    "Cyclo Cross|Yorkshire & Humber": 14,
    "Hill Climb|London & South East": 24,
    "Hill Climb|Yorkshire & Humber": 7,
    "Cyclo Cross|Eastern": 7,
    "Road|Wales": 1,
    "BMX|West Midlands": 1,
    "MTB|Eastern": 2,
    "Track|London & South East": 2,
    "Hill Climb|West Midlands": 7,
    "MTB|Scotland": 5,
    "Cyclo Cross|London & South East": 6,
    "Cyclo Cross|North East": 9,
    "Cyclo Cross|Wales": 4,
    "Cyclo Cross|Scotland": 8,
    "Hill Climb|South West": 14,
    "Road|East Midlands": 1,
    "Cyclo Cross|North West": 2,
    "Cyclo Cross|South": 9,
    "BMX|Eastern": 3,
    "MTB|West Midlands": 2,
    "Cyclo Cross|West Midlands": 10,
    "BMX|Scotland": 1,
    "Hill Climb|North West": 10,
    "Track|North West": 23,
    "Road|London & South East": 1,
    "Road|Eastern": 1,
    "Cyclo Cross|East Midlands": 7,
    "Time Trial|Scotland": 1,
    "Hill Climb|Wales": 4,
    "Hill Climb|Scotland": 1,
    "BMX|South": 7,
    "Hill Climb|East Midlands": 8,
    "Hill Climb|Eastern": 8,
    "Cyclo Cross|South West": 10,
    "Hill Climb|Central": 5,
    "MTB|North West": 1,
    "MTB|London & South East": 1,
    "Road|North East": 2,
    "BMX|North West": 1,
    "Track|Wales": 25,
    "Track|South": 1,
    "Road|Central": 3,
    "MTB|South": 3,
    "BMX|East Midlands": 1,
    "BMX|London & South East": 1
  },
  "last_build": "2025-09-18T02:25:15.823Z"
}