{
  "types": [
    "Road",
    "Track",
    "BMX",
    "MTB",
    "Cyclo Cross",
    "Speedway",
    "Time Trial",
    "Hill Climb"
  ],
  "regions": [
    "Central",
    "Eastern",
    "London & South East",
    "Midlands",
    "North East",
    "North West",
    "Scotland",
    "South",
    "South West",
    "Wales",
    "Yorkshire"
  ],
  "counts": {
    "Road": 7,
    "Track": 42,
    "BMX": 15,
    "MTB": 30,
    "Cyclo Cross": 114,
    "Speedway": 0,
    "Time Trial": 1,
    "Hill Climb": 1,
    "North West": 29,
    "Midlands": 40,
    "London & South East": 16,
    "Yorkshire": 17,
    "Eastern": 18,
    "South": 22,
    "Central": 15,
    "Wales": 10,
    "Scotland": 23,
    "North East": 9,
    "South West": 11,
    "Track|North West": 24,
    "Cyclo Cross|Midlands": 18,
    "Track|London & South East": 5,
    "Cyclo Cross|Yorkshire": 16,
    "Track|Midlands": 2,
    "Track|Eastern": 2,
    "MTB|Yorkshire": 1,
    "MTB|Midlands": 15,
    "Cyclo Cross|South": 14,
    "Cyclo Cross|Central": 12,
    "BMX|South": 5,
    "BMX|Midlands": 4,
    "Cyclo Cross|Eastern": 9,
    "Cyclo Cross|London & South East": 9,
    "Cyclo Cross|Wales": 4,
    "Cyclo Cross|North West": 3,
    "BMX|Scotland": 2,
    "BMX|Eastern": 3,
    "Hill Climb|London & South East": 1,
    "MTB|Eastern": 2,
    "MTB|Wales": 2,
    "Track|Scotland": 6,
    "Road|Wales": 1,
    "Road|Midlands": 1,
    "Cyclo Cross|North East": 9,
    "MTB|Scotland": 5,
    "Cyclo Cross|Scotland": 9,
    "Cyclo Cross|South West": 11,
    "MTB|North West": 1,
    "MTB|London & South East": 1,
    "BMX|North West": 1,
    "Road|Central": 3,
    "MTB|South": 3,
    "Track|Wales": 3,
    "Road|Eastern": 2,
    "Time Trial|Scotland": 1
  },
  "last_build": "2025-09-08T02:25:13.626Z"
}