{
  "disciplines": {
    "road": {
      "name": "Road",
      "count": 171
    },
    "track": {
      "name": "Track",
      "count": 114
    },
    "bmx": {
      "name": "BMX",
      "count": 19
    },
    "mtb": {
      "name": "MTB",
      "count": 129
    },
    "cyclo-cross": {
      "name": "Cyclo Cross",
      "count": 15
    },
    "speedway": {
      "name": "Speedway",
      "count": 9
    },
    "time-trial": {
      "name": "Time Trial",
      "count": 63
    },
    "hill-climb": {
      "name": "Hill Climb",
      "count": 159
    }
  },
  "last_build": "2026-03-10T04:09:16.181Z",
  "total_events": 679
}