{
  "disciplines": {
    "road": {
      "name": "Road",
      "count": 165
    },
    "track": {
      "name": "Track",
      "count": 120
    },
    "bmx": {
      "name": "BMX",
      "count": 26
    },
    "mtb": {
      "name": "MTB",
      "count": 129
    },
    "cyclo-cross": {
      "name": "Cyclo Cross",
      "count": 15
    },
    "speedway": {
      "name": "Speedway",
      "count": 5
    },
    "time-trial": {
      "name": "Time Trial",
      "count": 63
    },
    "hill-climb": {
      "name": "Hill Climb",
      "count": 159
    }
  },
  "last_build": "2026-03-08T14:15:39.993Z",
  "total_events": 682
}